design.sv
// Code your design here
`timescale 1ns / 1ps
module Car_Parking(
  input clk, sensor_entrance, sensor_exit, rst,
  input[3:0] password,
  output reg green_led, red_led
);
  parameter [2:0] IDLE = 3'b000,
  				  WAIT_PASSWORD = 3'b001,
  				  RIGHT_PASS = 3'b010,
  				  WRONG_PASS = 3'b011,
  				  STOP = 3'b100;
  
  reg [2:0] present_state, next_state;
  reg [4:0] counter_wait, counter_wrong, counter_stop, counter_led;
  parameter [3:0] default_password = 4'b1111;
  
  initial
    begin
      $dumpfile("dump.vcd");
      $dumpvars(1, Car_Parking);
    end
  
  always @(posedge clk or negedge rst)
    begin
      if (~rst)
        begin
          present_state = IDLE;
          green_led = 1'b0;
          red_led = 1'b1;
        end
      else
        begin
          present_state = next_state;
        end
    end
  
  always @(posedge clk or negedge rst)
    begin
      if (~rst)
        begin
          counter_wait = 0;
          counter_wrong = 0; 
          counter_stop = 0;
          counter_led = 0;
        end
      
      else if(present_state == WAIT_PASSWORD)
        begin
          counter_wait = counter_wait + 1;
          counter_wrong = 0;
          counter_stop = 0;
        end
      
      else if(present_state == WRONG_PASS)
        begin
          counter_wait = 0;
          counter_wrong = counter_wrong + 1;
          counter_stop = 0;
        end
      
      else if(present_state == STOP)
        begin
          counter_wait = 0;
          counter_wrong = 0;
          counter_stop = counter_stop + 1;
        end
      
      else
        begin
          counter_wait = 0;
          counter_wrong = 0;
          counter_stop = 0;
        end
      
      if(green_led == 1)
        counter_led = counter_led + 1;
      else
        counter_led = 0;
        
    end
  
  always @(*)
    begin
      case(present_state)
        IDLE:
          begin
            if (sensor_entrance)
              next_state = WAIT_PASSWORD;
            else
              next_state = present_state;
          end
        
        WAIT_PASSWORD:
          begin
            if (password == default_password)
              next_state = RIGHT_PASS;
            else if (counter_wait >= 10)
              next_state = IDLE;
            else if (password != default_password)
              next_state = WRONG_PASS;
            else
              next_state = present_state;
          end
        
        RIGHT_PASS:
          begin
            if(sensor_exit && sensor_entrance)
              next_state = STOP;
            else if(sensor_exit)
              next_state = IDLE;
            else
              next_state = present_state;
          end
        
        WRONG_PASS:
          begin
            if (password != default_password)
              next_state = present_state;
            else if(password == default_password)
              next_state = RIGHT_PASS;
            else if(counter_wrong >= 10)
              next_state = IDLE;
          end
        
        STOP:
          begin
            if (password != default_password)
              next_state = present_state;
            else if(password == default_password)
              next_state = RIGHT_PASS;
            else if(counter_stop >= 10)
              next_state = IDLE;
          end
        
        default:
          next_state = IDLE;  
      endcase
    end
  
  always @(*)
    begin
      if(present_state == RIGHT_PASS && sensor_exit == 1'b1)
        begin
          green_led = 1'b1;
          red_led = 1'b0;
        end
      
      else if(counter_led >= 10)
        begin
          green_led = 1'b0;
          red_led = 1'b1;
        end
    end
  
endmodule

testbench.sv
// Code your testbench here
// or browse Examples
`timescale 1ns / 1ps
module tb;
  reg clk, sensor_entrance, sensor_exit, rst;
  reg[3:0] password;
  wire green_led, red_led;
  
  Car_Parking cp(
    clk, sensor_entrance, sensor_exit, rst,
    password,
    green_led, red_led
  );
  
  always #5 clk = ~clk;
  
  initial
    begin
      $monitor("Time = %0t clk = %0d sensor_entrance = %0d sensor_exit = %0d rst = %0d password = %0d green_led = %0d red_led = %0d", $time, clk, sensor_entrance, sensor_exit, rst, password, green_led, red_led);
      
      clk = 1'b0;
      rst = 1'b1;
      #20;
      
      rst = 1'b0;
      #20;
      
      rst = 1'b1;
      sensor_entrance = 1'b1;
      #200
      
      sensor_entrance = 1'b1;
      #20;
      
      sensor_entrance = 1'b0;
      password = 4'b0000;
      #50;
      
      password = 4'b1111;
      #20;
      
      password = 4'b0000;
      #20
      
      sensor_entrance = 1'b1;
      sensor_exit = 1'b1;
      #20
      
      password = 4'b1111;
      sensor_entrance = 1'b0;
      sensor_exit = 1'b0;
      #20
      
      sensor_exit = 1'b1;
      #100;
      
      
      $finish;     
    end
    
endmodule

dump.vcd
$date
	Sat Dec 26 16:33:52 2020
$end
$version
	Icarus Verilog
$end
$timescale
	1ps
$end
$scope module tb $end
$scope module cp $end
$var wire 1 ! clk $end
$var wire 4 " password [3:0] $end
$var wire 1 # rst $end
$var wire 1 $ sensor_entrance $end
$var wire 1 % sensor_exit $end
$var reg 5 & counter_led [4:0] $end
$var reg 5 ' counter_stop [4:0] $end
$var reg 5 ( counter_wait [4:0] $end
$var reg 5 ) counter_wrong [4:0] $end
$var reg 1 * green_led $end
$var reg 3 + next_state [2:0] $end
$var reg 3 , present_state [2:0] $end
$var reg 1 - red_led $end
$upscope $end
$upscope $end
$enddefinitions $end
#0
$dumpvars
x-
bx ,
bx +
x*
bx )
bx (
bx '
bx &
x%
x$
1#
bx "
0!
$end
#5000
b0 +
b0 &
b0 '
b0 )
b0 (
1!
#10000
0!
#15000
b0 ,
1!
#20000
1-
0*
0!
0#
#25000
1!
#30000
0!
#35000
1!
#40000
b1 +
0!
1$
1#
#45000
b1 (
b1 ,
1!
#50000
0!
#55000
b10 (
1!
#60000
0!
#65000
b11 (
1!
#70000
0!
#75000
b100 (
1!
#80000
0!
#85000
b101 (
1!
#90000
0!
#95000
b110 (
1!
#100000
0!
#105000
b111 (
1!
#110000
0!
#115000
b1000 (
1!
#120000
0!
#125000
b1001 (
1!
#130000
0!
#135000
b0 +
b1010 (
1!
#140000
0!
#145000
b1 +
b0 (
b0 ,
1!
#150000
0!
#155000
b1 ,
1!
#160000
0!
#165000
b1 (
1!
#170000
0!
#175000
b10 (
1!
#180000
0!
#185000
b11 (
1!
#190000
0!
#195000
b100 (
1!
#200000
0!
#205000
b101 (
1!
#210000
0!
#215000
b110 (
1!
#220000
0!
#225000
b111 (
1!
#230000
0!
#235000
b1000 (
1!
#240000
0!
#245000
b1001 (
1!
#250000
0!
#255000
b0 +
b1010 (
1!
#260000
0!
b0 "
0$
#265000
b0 (
b0 ,
1!
#270000
0!
#275000
1!
#280000
0!
#285000
1!
#290000
0!
#295000
1!
#300000
0!
#305000
1!
#310000
0!
b1111 "
#315000
1!
#320000
0!
#325000
1!
#330000
0!
b0 "
#335000
1!
#340000
0!
#345000
1!
#350000
b1 +
0!
1%
1$
#355000
b11 +
b1 ,
1!
#360000
0!
#365000
b1 )
b11 ,
1!
#370000
b10 +
0!
0%
0$
b1111 "
#375000
b10 ,
b10 )
1!
#380000
0!
#385000
b0 )
1!
#390000
0-
1*
b0 +
0!
1%
#395000
b0 ,
b1 &
1!
#400000
0!
#405000
b10 &
1!
#410000
0!
#415000
b11 &
1!
#420000
0!
#425000
b100 &
1!
#430000
0!
#435000
b101 &
1!
#440000
0!
#445000
b110 &
1!
#450000
0!
#455000
b111 &
1!
#460000
0!
#465000
b1000 &
1!
#470000
0!
#475000
b1001 &
1!
#480000
0!
#485000
1-
0*
b1010 &
1!
